I2c.v
module i2c_write (
    input clk_50mhz,
    input reset,
    input start,
    input [6:0] slave_addr,
    input [7:0] pointer_addr,
    input [7:0] data_in,
    output reg busy,
    output reg done,
    inout scl,
    inout sda
);

    reg [7:0] clk_count;
    reg timing_tick;
    reg sda_oe;
    reg scl_oe;

    reg [7:0] data_reg;
    reg [7:0] pointer_reg;
    reg [7:0] addr_reg;
    reg [3:0] bit_count;

    parameter IDLE = 5'd0;
    parameter START_STATE = 5'd1;
    parameter ADDR_LOW = 5'd2;
    parameter ADDR_HIGH = 5'd3;
    parameter ADDR_ACK_LOW = 5'd4;
    parameter ADDR_ACK_HIGH = 5'd5;
    parameter POINTER_LOW = 5'd6;
    parameter POINTER_HIGH = 5'd7;
    parameter POINTER_ACK_LOW = 5'd8;
    parameter POINTER_ACK_HIGH = 5'd9;
    parameter DATA_LOW = 5'd10;
    parameter DATA_HIGH = 5'd11;
    parameter DATA_ACK_LOW = 5'd12;
    parameter DATA_ACK_HIGH = 5'd13;
    parameter STOP_LOW = 5'd14;
    parameter STOP_HIGH = 5'd15;

    reg [4:0] state;
    reg [4:0] next_state;

    assign scl = scl_oe ? 1'b0 : 1'bz;
    assign sda = sda_oe ? 1'b0 : 1'bz;

    always @(posedge clk_50mhz or posedge reset) begin
        if (reset) begin
            clk_count <= 8'd0;
            timing_tick <= 1'b0;
        end
        else begin
            timing_tick <= 1'b0;

            if (clk_count == 8'd61) begin
                clk_count <= 8'd0;
                timing_tick <= 1'b1;
            end
            else begin
                clk_count <= clk_count + 1'b1;
            end
        end
    end

    always @(posedge clk_50mhz or posedge reset) begin
        if (reset) begin
            state <= IDLE;
            addr_reg <= 8'd0;
            pointer_reg <= 8'd0;
            data_reg <= 8'd0;
            bit_count <= 4'd7;
            busy <= 1'b0;
            done <= 1'b0;
        end
        else begin
            done <= 1'b0;

            if (timing_tick) begin
                state <= next_state;

                if ((state == IDLE) && start) begin
                    addr_reg <= {slave_addr, 1'b0};
                    pointer_reg <= pointer_addr;
                    data_reg <= data_in;
                    bit_count <= 4'd7;
                    busy <= 1'b1;
                    done <= 1'b0;
                end

                else if (state == ADDR_HIGH) begin
                    if (bit_count != 0)
                        bit_count <= bit_count - 1'b1;
                    else
                        bit_count <= 4'd7;
                end

                else if (state == POINTER_HIGH) begin
                    if (bit_count != 0)
                        bit_count <= bit_count - 1'b1;
                    else
                        bit_count <= 4'd7;
                end

                else if (state == DATA_HIGH) begin
                    if (bit_count != 0)
                        bit_count <= bit_count - 1'b1;
                    else
                        bit_count <= 4'd7;
                end

                else if (state == STOP_HIGH) begin
                    busy <= 1'b0;
                    done <= 1'b1;
                end
            end
        end
    end

    always @(*) begin
        next_state = state;

        case (state)

            IDLE: begin
                if (start)
                    next_state = START_STATE;
                else
                    next_state = IDLE;
            end

            START_STATE: begin
                next_state = ADDR_LOW;
            end

            ADDR_LOW: begin
                next_state = ADDR_HIGH;
            end

            ADDR_HIGH: begin
                if (bit_count == 4'd0)
                    next_state = ADDR_ACK_LOW;
                else
                    next_state = ADDR_LOW;
            end

            ADDR_ACK_LOW: begin
                next_state = ADDR_ACK_HIGH;
            end

            ADDR_ACK_HIGH: begin
                if (sda == 1'b0)
                    next_state = POINTER_LOW;
                else
                    next_state = STOP_LOW;
            end

            POINTER_LOW: begin
                next_state = POINTER_HIGH;
            end

            POINTER_HIGH: begin
                if (bit_count == 4'd0)
                    next_state = POINTER_ACK_LOW;
                else
                    next_state = POINTER_LOW;
            end

            POINTER_ACK_LOW: begin
                next_state = POINTER_ACK_HIGH;
            end

            POINTER_ACK_HIGH: begin
                if (sda == 1'b0)
                    next_state = DATA_LOW;
                else
                    next_state = STOP_LOW;
            end

            DATA_LOW: begin
                next_state = DATA_HIGH;
            end

            DATA_HIGH: begin
                if (bit_count == 4'd0)
                    next_state = DATA_ACK_LOW;
                else
                    next_state = DATA_LOW;
            end

            DATA_ACK_LOW: begin
                next_state = DATA_ACK_HIGH;
            end

            DATA_ACK_HIGH: begin
                next_state = STOP_LOW;
            end

            STOP_LOW: begin
                next_state = STOP_HIGH;
            end

            STOP_HIGH: begin
                next_state = IDLE;
            end

            default: begin
                next_state = IDLE;
            end

        endcase
    end

    always @(*) begin
        scl_oe = 1'b0;
        sda_oe = 1'b0;

        case (state)

            IDLE: begin
                scl_oe = 1'b0;
                sda_oe = 1'b0;
            end

            START_STATE: begin
                scl_oe = 1'b0;
                sda_oe = 1'b1;
            end

            ADDR_LOW: begin
                scl_oe = 1'b1;

                if (addr_reg[bit_count] == 1'b0)
                    sda_oe = 1'b1;
                else
                    sda_oe = 1'b0;
            end

            ADDR_HIGH: begin
                scl_oe = 1'b0;

                if (addr_reg[bit_count] == 1'b0)
                    sda_oe = 1'b1;
                else
                    sda_oe = 1'b0;
            end

            ADDR_ACK_LOW: begin
                scl_oe = 1'b1;
                sda_oe = 1'b0;
            end

            ADDR_ACK_HIGH: begin
                scl_oe = 1'b0;
                sda_oe = 1'b0;
            end

            POINTER_LOW: begin
                scl_oe = 1'b1;

                if (pointer_reg[bit_count] == 1'b0)
                    sda_oe = 1'b1;
                else
                    sda_oe = 1'b0;
            end

            POINTER_HIGH: begin
                scl_oe = 1'b0;

                if (pointer_reg[bit_count] == 1'b0)
                    sda_oe = 1'b1;
                else
                    sda_oe = 1'b0;
            end

            POINTER_ACK_LOW: begin
                scl_oe = 1'b1;
                sda_oe = 1'b0;
            end

            POINTER_ACK_HIGH: begin
                scl_oe = 1'b0;
                sda_oe = 1'b0;
            end

            DATA_LOW: begin
                scl_oe = 1'b1;

                if (data_reg[bit_count] == 1'b0)
                    sda_oe = 1'b1;
                else
                    sda_oe = 1'b0;
            end

            DATA_HIGH: begin
                scl_oe = 1'b0;

                if (data_reg[bit_count] == 1'b0)
                    sda_oe = 1'b1;
                else
                    sda_oe = 1'b0;
            end

            DATA_ACK_LOW: begin
                scl_oe = 1'b1;
                sda_oe = 1'b0;
            end

            DATA_ACK_HIGH: begin
                scl_oe = 1'b0;
                sda_oe = 1'b0;
            end

            STOP_LOW: begin
                scl_oe = 1'b1;
                sda_oe = 1'b1;
            end

            STOP_HIGH: begin
                scl_oe = 1'b0;
                sda_oe = 1'b0;
            end

            default: begin
                scl_oe = 1'b0;
                sda_oe = 1'b0;
            end

        endcase
    end

endmodule

I2c_tb.v
`timescale 1ns/1ps

module i2c_write_tb;

    reg clk_50mhz;
    reg reset;
    reg start;

    reg [6:0] slave_addr;
    reg [7:0] pointer_addr;
    reg [7:0] data_in;

    wire busy;
    wire done;

    wire scl;
    wire sda;

    reg slave_ack;

    i2c_write uut (
        .clk_50mhz(clk_50mhz),
        .reset(reset),
        .start(start),
        .slave_addr(slave_addr),
        .pointer_addr(pointer_addr),
        .data_in(data_in),
        .busy(busy),
        .done(done),
        .scl(scl),
        .sda(sda)
    );

    pullup(scl);
    pullup(sda);

    assign sda = slave_ack ? 1'b0 : 1'bz;

    initial begin
        clk_50mhz = 1'b0;
        forever #10 clk_50mhz = ~clk_50mhz;
    end

    initial begin

        reset = 1'b1;
        start = 1'b0;

        slave_addr  = 7'h50;
        pointer_addr = 8'h20;
        data_in      = 8'hA5;

        #100;

        reset = 1'b0;

        #100;

        $display("");
        $display("======================================");
        $display("       I2C WRITE TRANSACTION");
        $display("======================================");
        $display("ADDRESS = %h", slave_addr);
        $display("POINTER = %h", pointer_addr);
        $display("DATA    = %h", data_in);
        $display("======================================");

        start = 1'b1;

        #2000;

        start = 1'b0;

        wait(done == 1'b1);

        #100;

        $display("");
        $display("======================================");
        $display(" I2C WRITE TRANSACTION COMPLETED");
        $display("======================================");
        $display("BUSY = %b", busy);
        $display("DONE = %b", done);
        $display("======================================");

        #100;

        $finish;
    end
    always @(*) begin
    case (uut.state)

        uut.ADDR_ACK_LOW,
        uut.ADDR_ACK_HIGH:
            slave_ack = 1'b1;

        uut.POINTER_ACK_LOW,
        uut.POINTER_ACK_HIGH:
            slave_ack = 1'b1;

        uut.DATA_ACK_LOW,
        uut.DATA_ACK_HIGH:
            slave_ack = 1'b1;

        default:
            slave_ack = 1'b0;

    endcase
end

   
    initial begin

        $monitor(
            "TIME=%0t | STATE=%0d | SCL=%b | SDA=%b | BIT=%0d | BUSY=%b | DONE=%b",
            $time,
            uut.state,
            scl,
            sda,
            uut.bit_count,
            busy,
            done
        );

    end

    initial begin
        $dumpfile("i2c_write.vcd");
        $dumpvars(0, i2c_write_tb);
    end

    initial begin

        #300000;

        $display("");
        $display("ERROR: I2C TRANSACTION TIMEOUT");
        $display("");

        $finish;

    end

endmodule

i2c_write.vcd
$date
	Fri Aug 21 04:39:22 2026
$end
$version
	Icarus Verilog
$end
$timescale
	1ps
$end
$scope module i2c_write_tb $end
$var wire 1 ! scl $end
$var wire 1 " sda $end
$var wire 1 # done $end
$var wire 1 $ busy $end
$var reg 1 % clk_50mhz $end
$var reg 8 & data_in [7:0] $end
$var reg 8 ' pointer_addr [7:0] $end
$var reg 1 ( reset $end
$var reg 1 ) slave_ack $end
$var reg 7 * slave_addr [6:0] $end
$var reg 1 + start $end
$scope module uut $end
$var wire 1 % clk_50mhz $end
$var wire 8 , data_in [7:0] $end
$var wire 8 - pointer_addr [7:0] $end
$var wire 1 ( reset $end
$var wire 1 ! scl $end
$var wire 1 " sda $end
$var wire 7 . slave_addr [6:0] $end
$var wire 1 + start $end
$var parameter 5 / ADDR_ACK_HIGH $end
$var parameter 5 0 ADDR_ACK_LOW $end
$var parameter 5 1 ADDR_HIGH $end
$var parameter 5 2 ADDR_LOW $end
$var parameter 5 3 DATA_ACK_HIGH $end
$var parameter 5 4 DATA_ACK_LOW $end
$var parameter 5 5 DATA_HIGH $end
$var parameter 5 6 DATA_LOW $end
$var parameter 5 7 IDLE $end
$var parameter 5 8 POINTER_ACK_HIGH $end
$var parameter 5 9 POINTER_ACK_LOW $end
$var parameter 5 : POINTER_HIGH $end
$var parameter 5 ; POINTER_LOW $end
$var parameter 5 < START_STATE $end
$var parameter 5 = STOP_HIGH $end
$var parameter 5 > STOP_LOW $end
$var reg 8 ? addr_reg [7:0] $end
$var reg 4 @ bit_count [3:0] $end
$var reg 1 $ busy $end
$var reg 8 A clk_count [7:0] $end
$var reg 8 B data_reg [7:0] $end
$var reg 1 # done $end
$var reg 5 C next_state [4:0] $end
$var reg 8 D pointer_reg [7:0] $end
$var reg 1 E scl_oe $end
$var reg 1 F sda_oe $end
$var reg 5 G state [4:0] $end
$var reg 1 H timing_tick $end
$upscope $end
$upscope $end
$enddefinitions $end
$comment Show the parameter values. $end
$dumpall
b1110 >
b1111 =
b1 <
b110 ;
b111 :
b1000 9
b1001 8
b0 7
b1010 6
b1011 5
b1100 4
b1101 3
b10 2
b11 1
b100 0
b101 /
$end
#0
$dumpvars
0H
b0 G
0F
0E
b0 D
b0 C
b0 B
b0 A
b111 @
b0 ?
b1010000 .
b100000 -
b10100101 ,
0+
b1010000 *
0)
1(
b100000 '
b10100101 &
0%
0$
0#
1"
1!
$end
#10000
1%
#20000
0%
#30000
1%
#40000
0%
#50000
1%
#60000
0%
#70000
1%
#80000
0%
#90000
1%
#100000
0%
0(
#110000
b1 A
1%
#120000
0%
#130000
b10 A
1%
#140000
0%
#150000
b11 A
1%
#160000
0%
#170000
b100 A
1%
#180000
0%
#190000
b101 A
1%
#200000
b1 C
0%
1+
#210000
b110 A
1%
#220000
0%
#230000
b111 A
1%
#240000
0%
#250000
b1000 A
1%
#260000
0%
#270000
b1001 A
1%
#280000
0%
#290000
b1010 A
1%
#300000
0%
#310000
b1011 A
1%
#320000
0%
#330000
b1100 A
1%
#340000
0%
#350000
b1101 A
1%
#360000
0%
#370000
b1110 A
1%
#380000
0%
#390000
b1111 A
1%
#400000
0%
#410000
b10000 A
1%
#420000
0%
#430000
b10001 A
1%
#440000
0%
#450000
b10010 A
1%
#460000
0%
#470000
b10011 A
1%
#480000
0%
#490000
b10100 A
1%
#500000
0%
#510000
b10101 A
1%
#520000
0%
#530000
b10110 A
1%
#540000
0%
#550000
b10111 A
1%
#560000
0%
#570000
b11000 A
1%
#580000
0%
#590000
b11001 A
1%
#600000
0%
#610000
b11010 A
1%
#620000
0%
#630000
b11011 A
1%
#640000
0%
#650000
b11100 A
1%
#660000
0%
#670000
b11101 A
1%
#680000
0%
#690000
b11110 A
1%
#700000
0%
#710000
b11111 A
1%
#720000
0%
#730000
b100000 A
1%
#740000
0%
#750000
b100001 A
1%
#760000
0%
#770000
b100010 A
1%
#780000
0%
#790000
b100011 A
1%
#800000
0%
#810000
b100100 A
1%
#820000
0%
#830000
b100101 A
1%
#840000
0%
#850000
b100110 A
1%
#860000
0%
#870000
b100111 A
1%
#880000
0%
#890000
b101000 A
1%
#900000
0%
#910000
b101001 A
1%
#920000
0%
#930000
b101010 A
1%
#940000
0%
#950000
b101011 A
1%
#960000
0%
#970000
b101100 A
1%
#980000
0%
#990000
b101101 A
1%
#1000000
0%
#1010000
b101110 A
1%
#1020000
0%
#1030000
b101111 A
1%
#1040000
0%
#1050000
b110000 A
1%
#1060000
0%
#1070000
b110001 A
1%
#1080000
0%
#1090000
b110010 A
1%
#1100000
0%
#1110000
b110011 A
1%
#1120000
0%
#1130000
b110100 A
1%
#1140000
0%
#1150000
b110101 A
1%
#1160000
0%
#1170000
b110110 A
1%
#1180000
0%
#1190000
b110111 A
1%
#1200000
0%
#1210000
b111000 A
1%
#1220000
0%
#1230000
b111001 A
1%
#1240000
0%
#1250000
b111010 A
1%
#1260000
0%
#1270000
b111011 A
1%
#1280000
0%
#1290000
b111100 A
1%
#1300000
0%
#1310000
b111101 A
1%
#1320000
0%
#1330000
1H
b0 A
1%
#1340000
0%
#1350000
0"
1F
b10 C
b1 A
0H
1$
b10100101 B
b100000 D
b10100000 ?
b1 G
1%
#1360000
0%
#1370000
b10 A
1%
#1380000
0%
#1390000
b11 A
1%
#1400000
0%
#1410000
b100 A
1%
#1420000
0%
#1430000
b101 A
1%
#1440000
0%
#1450000
b110 A
1%
#1460000
0%
#1470000
b111 A
1%
#1480000
0%
#1490000
b1000 A
1%
#1500000
0%
#1510000
b1001 A
1%
#1520000
0%
#1530000
b1010 A
1%
#1540000
0%
#1550000
b1011 A
1%
#1560000
0%
#1570000
b1100 A
1%
#1580000
0%
#1590000
b1101 A
1%
#1600000
0%
#1610000
b1110 A
1%
#1620000
0%
#1630000
b1111 A
1%
#1640000
0%
#1650000
b10000 A
1%
#1660000
0%
#1670000
b10001 A
1%
#1680000
0%
#1690000
b10010 A
1%
#1700000
0%
#1710000
b10011 A
1%
#1720000
0%
#1730000
b10100 A
1%
#1740000
0%
#1750000
b10101 A
1%
#1760000
0%
#1770000
b10110 A
1%
#1780000
0%
#1790000
b10111 A
1%
#1800000
0%
#1810000
b11000 A
1%
#1820000
0%
#1830000
b11001 A
1%
#1840000
0%
#1850000
b11010 A
1%
#1860000
0%
#1870000
b11011 A
1%
#1880000
0%
#1890000
b11100 A
1%
#1900000
0%
#1910000
b11101 A
1%
#1920000
0%
#1930000
b11110 A
1%
#1940000
0%
#1950000
b11111 A
1%
#1960000
0%
#1970000
b100000 A
1%
#1980000
0%
#1990000
b100001 A
1%
#2000000
0%
#2010000
b100010 A
1%
#2020000
0%
#2030000
b100011 A
1%
#2040000
0%
#2050000
b100100 A
1%
#2060000
0%
#2070000
b100101 A
1%
#2080000
0%
#2090000
b100110 A
1%
#2100000
0%
#2110000
b100111 A
1%
#2120000
0%
#2130000
b101000 A
1%
#2140000
0%
#2150000
b101001 A
1%
#2160000
0%
#2170000
b101010 A
1%
#2180000
0%
#2190000
b101011 A
1%
#2200000
b10 C
0%
0+
#2210000
b101100 A
1%
#2220000
0%
#2230000
b101101 A
1%
#2240000
0%
#2250000
b101110 A
1%
#2260000
0%
#2270000
b101111 A
1%
#2280000
0%
#2290000
b110000 A
1%
#2300000
0%
#2310000
b110001 A
1%
#2320000
0%
#2330000
b110010 A
1%
#2340000
0%
#2350000
b110011 A
1%
#2360000
0%
#2370000
b110100 A
1%
#2380000
0%
#2390000
b110101 A
1%
#2400000
0%
#2410000
b110110 A
1%
#2420000
0%
#2430000
b110111 A
1%
#2440000
0%
#2450000
b111000 A
1%
#2460000
0%
#2470000
b111001 A
1%
#2480000
0%
#2490000
b111010 A
1%
#2500000
0%
#2510000
b111011 A
1%
#2520000
0%
#2530000
b111100 A
1%
#2540000
0%
#2550000
b111101 A
1%
#2560000
0%
#2570000
1H
b0 A
1%
#2580000
0%
#2590000
0!
1"
1E
0F
b11 C
b1 A
0H
b10 G
1%
#2600000
0%
#2610000
b10 A
1%
#2620000
0%
#2630000
b11 A
1%
#2640000
0%
#2650000
b100 A
1%
#2660000
0%
#2670000
b101 A
1%
#2680000
0%
#2690000
b110 A
1%
#2700000
0%
#2710000
b111 A
1%
#2720000
0%
#2730000
b1000 A
1%
#2740000
0%
#2750000
b1001 A
1%
#2760000
0%
#2770000
b1010 A
1%
#2780000
0%
#2790000
b1011 A
1%
#2800000
0%
#2810000
b1100 A
1%
#2820000
0%
#2830000
b1101 A
1%
#2840000
0%
#2850000
b1110 A
1%
#2860000
0%
#2870000
b1111 A
1%
#2880000
0%
#2890000
b10000 A
1%
#2900000
0%
#2910000
b10001 A
1%
#2920000
0%
#2930000
b10010 A
1%
#2940000
0%
#2950000
b10011 A
1%
#2960000
0%
#2970000
b10100 A
1%
#2980000
0%
#2990000
b10101 A
1%
#3000000
0%
#3010000
b10110 A
1%
#3020000
0%
#3030000
b10111 A
1%
#3040000
0%
#3050000
b11000 A
1%
#3060000
0%
#3070000
b11001 A
1%
#3080000
0%
#3090000
b11010 A
1%
#3100000
0%
#3110000
b11011 A
1%
#3120000
0%
#3130000
b11100 A
1%
#3140000
0%
#3150000
b11101 A
1%
#3160000
0%
#3170000
b11110 A
1%
#3180000
0%
#3190000
b11111 A
1%
#3200000
0%
#3210000
b100000 A
1%
#3220000
0%
#3230000
b100001 A
1%
#3240000
0%
#3250000
b100010 A
1%
#3260000
0%
#3270000
b100011 A
1%
#3280000
0%
#3290000
b100100 A
1%
#3300000
0%
#3310000
b100101 A
1%
#3320000
0%
#3330000
b100110 A
1%
#3340000
0%
#3350000
b100111 A
1%
#3360000
0%
#3370000
b101000 A
1%
#3380000
0%
#3390000
b101001 A
1%
#3400000
0%
#3410000
b101010 A
1%
#3420000
0%
#3430000
b101011 A
1%
#3440000
0%
#3450000
b101100 A
1%
#3460000
0%
#3470000
b101101 A
1%
#3480000
0%
#3490000
b101110 A
1%
#3500000
0%
#3510000
b101111 A
1%
#3520000
0%
#3530000
b110000 A
1%
#3540000
0%
#3550000
b110001 A
1%
#3560000
0%
#3570000
b110010 A
1%
#3580000
0%
#3590000
b110011 A
1%
#3600000
0%
#3610000
b110100 A
1%
#3620000
0%
#3630000
b110101 A
1%
#3640000
0%
#3650000
b110110 A
1%
#3660000
0%
#3670000
b110111 A
1%
#3680000
0%
#3690000
b111000 A
1%
#3700000
0%
#3710000
b111001 A
1%
#3720000
0%
#3730000
b111010 A
1%
#3740000
0%
#3750000
b111011 A
1%
#3760000
0%
#3770000
b111100 A
1%
#3780000
0%
#3790000
b111101 A
1%
#3800000
0%
#3810000
1H
b0 A
1%
#3820000
0%
#3830000
1!
0E
b10 C
b1 A
0H
b11 G
1%
#3840000
0%
#3850000
b10 A
1%
#3860000
0%
#3870000
b11 A
1%
#3880000
0%
#3890000
b100 A
1%
#3900000
0%
#3910000
b101 A
1%
#3920000
0%
#3930000
b110 A
1%
#3940000
0%
#3950000
b111 A
1%
#3960000
0%
#3970000
b1000 A
1%
#3980000
0%
#3990000
b1001 A
1%
#4000000
0%
#4010000
b1010 A
1%
#4020000
0%
#4030000
b1011 A
1%
#4040000
0%
#4050000
b1100 A
1%
#4060000
0%
#4070000
b1101 A
1%
#4080000
0%
#4090000
b1110 A
1%
#4100000
0%
#4110000
b1111 A
1%
#4120000
0%
#4130000
b10000 A
1%
#4140000
0%
#4150000
b10001 A
1%
#4160000
0%
#4170000
b10010 A
1%
#4180000
0%
#4190000
b10011 A
1%
#4200000
0%
#4210000
b10100 A
1%
#4220000
0%
#4230000
b10101 A
1%
#4240000
0%
#4250000
b10110 A
1%
#4260000
0%
#4270000
b10111 A
1%
#4280000
0%
#4290000
b11000 A
1%
#4300000
0%
#4310000
b11001 A
1%
#4320000
0%
#4330000
b11010 A
1%
#4340000
0%
#4350000
b11011 A
1%
#4360000
0%
#4370000
b11100 A
1%
#4380000
0%
#4390000
b11101 A
1%
#4400000
0%
#4410000
b11110 A
1%
#4420000
0%
#4430000
b11111 A
1%
#4440000
0%
#4450000
b100000 A
1%
#4460000
0%
#4470000
b100001 A
1%
#4480000
0%
#4490000
b100010 A
1%
#4500000
0%
#4510000
b100011 A
1%
#4520000
0%
#4530000
b100100 A
1%
#4540000
0%
#4550000
b100101 A
1%
#4560000
0%
#4570000
b100110 A
1%
#4580000
0%
#4590000
b100111 A
1%
#4600000
0%
#4610000
b101000 A
1%
#4620000
0%
#4630000
b101001 A
1%
#4640000
0%
#4650000
b101010 A
1%
#4660000
0%
#4670000
b101011 A
1%
#4680000
0%
#4690000
b101100 A
1%
#4700000
0%
#4710000
b101101 A
1%
#4720000
0%
#4730000
b101110 A
1%
#4740000
0%
#4750000
b101111 A
1%
#4760000
0%
#4770000
b110000 A
1%
#4780000
0%
#4790000
b110001 A
1%
#4800000
0%
#4810000
b110010 A
1%
#4820000
0%
#4830000
b110011 A
1%
#4840000
0%
#4850000
b110100 A
1%
#4860000
0%
#4870000
b110101 A
1%
#4880000
0%
#4890000
b110110 A
1%
#4900000
0%
#4910000
b110111 A
1%
#4920000
0%
#4930000
b111000 A
1%
#4940000
0%
#4950000
b111001 A
1%
#4960000
0%
#4970000
b111010 A
1%
#4980000
0%
#4990000
b111011 A
1%
#5000000
0%
#5010000
b111100 A
1%
#5020000
0%
#5030000
b111101 A
1%
#5040000
0%
#5050000
1H
b0 A
1%
#5060000
0%
#5070000
0"
0!
1F
1E
b11 C
b1 A
0H
b110 @
b10 G
1%
#5080000
0%
#5090000
b10 A
1%
#5100000
0%
#5110000
b11 A
1%
#5120000
0%
#5130000
b100 A
1%
#5140000
0%
#5150000
b101 A
1%
#5160000
0%
#5170000
b110 A
1%
#5180000
0%
#5190000
b111 A
1%
#5200000
0%
#5210000
b1000 A
1%
#5220000
0%
#5230000
b1001 A
1%
#5240000
0%
#5250000
b1010 A
1%
#5260000
0%
#5270000
b1011 A
1%
#5280000
0%
#5290000
b1100 A
1%
#5300000
0%
#5310000
b1101 A
1%
#5320000
0%
#5330000
b1110 A
1%
#5340000
0%
#5350000
b1111 A
1%
#5360000
0%
#5370000
b10000 A
1%
#5380000
0%
#5390000
b10001 A
1%
#5400000
0%
#5410000
b10010 A
1%
#5420000
0%
#5430000
b10011 A
1%
#5440000
0%
#5450000
b10100 A
1%
#5460000
0%
#5470000
b10101 A
1%
#5480000
0%
#5490000
b10110 A
1%
#5500000
0%
#5510000
b10111 A
1%
#5520000
0%
#5530000
b11000 A
1%
#5540000
0%
#5550000
b11001 A
1%
#5560000
0%
#5570000
b11010 A
1%
#5580000
0%
#5590000
b11011 A
1%
#5600000
0%
#5610000
b11100 A
1%
#5620000
0%
#5630000
b11101 A
1%
#5640000
0%
#5650000
b11110 A
1%
#5660000
0%
#5670000
b11111 A
1%
#5680000
0%
#5690000
b100000 A
1%
#5700000
0%
#5710000
b100001 A
1%
#5720000
0%
#5730000
b100010 A
1%
#5740000
0%
#5750000
b100011 A
1%
#5760000
0%
#5770000
b100100 A
1%
#5780000
0%
#5790000
b100101 A
1%
#5800000
0%
#5810000
b100110 A
1%
#5820000
0%
#5830000
b100111 A
1%
#5840000
0%
#5850000
b101000 A
1%
#5860000
0%
#5870000
b101001 A
1%
#5880000
0%
#5890000
b101010 A
1%
#5900000
0%
#5910000
b101011 A
1%
#5920000
0%
#5930000
b101100 A
1%
#5940000
0%
#5950000
b101101 A
1%
#5960000
0%
#5970000
b101110 A
1%
#5980000
0%
#5990000
b101111 A
1%
#6000000
0%
#6010000
b110000 A
1%
#6020000
0%
#6030000
b110001 A
1%
#6040000
0%
#6050000
b110010 A
1%
#6060000
0%
#6070000
b110011 A
1%
#6080000
0%
#6090000
b110100 A
1%
#6100000
0%
#6110000
b110101 A
1%
#6120000
0%
#6130000
b110110 A
1%
#6140000
0%
#6150000
b110111 A
1%
#6160000
0%
#6170000
b111000 A
1%
#6180000
0%
#6190000
b111001 A
1%
#6200000
0%
#6210000
b111010 A
1%
#6220000
0%
#6230000
b111011 A
1%
#6240000
0%
#6250000
b111100 A
1%
#6260000
0%
#6270000
b111101 A
1%
#6280000
0%
#6290000
1H
b0 A
1%
#6300000
0%
#6310000
1!
1F
0E
b10 C
b1 A
0H
b11 G
1%
#6320000
0%
#6330000
b10 A
1%
#6340000
0%
#6350000
b11 A
1%
#6360000
0%
#6370000
b100 A
1%
#6380000
0%
#6390000
b101 A
1%
#6400000
0%
#6410000
b110 A
1%
#6420000
0%
#6430000
b111 A
1%
#6440000
0%
#6450000
b1000 A
1%
#6460000
0%
#6470000
b1001 A
1%
#6480000
0%
#6490000
b1010 A
1%
#6500000
0%
#6510000
b1011 A
1%
#6520000
0%
#6530000
b1100 A
1%
#6540000
0%
#6550000
b1101 A
1%
#6560000
0%
#6570000
b1110 A
1%
#6580000
0%
#6590000
b1111 A
1%
#6600000
0%
#6610000
b10000 A
1%
#6620000
0%
#6630000
b10001 A
1%
#6640000
0%
#6650000
b10010 A
1%
#6660000
0%
#6670000
b10011 A
1%
#6680000
0%
#6690000
b10100 A
1%
#6700000
0%
#6710000
b10101 A
1%
#6720000
0%
#6730000
b10110 A
1%
#6740000
0%
#6750000
b10111 A
1%
#6760000
0%
#6770000
b11000 A
1%
#6780000
0%
#6790000
b11001 A
1%
#6800000
0%
#6810000
b11010 A
1%
#6820000
0%
#6830000
b11011 A
1%
#6840000
0%
#6850000
b11100 A
1%
#6860000
0%
#6870000
b11101 A
1%
#6880000
0%
#6890000
b11110 A
1%
#6900000
0%
#6910000
b11111 A
1%
#6920000
0%
#6930000
b100000 A
1%
#6940000
0%
#6950000
b100001 A
1%
#6960000
0%
#6970000
b100010 A
1%
#6980000
0%
#6990000
b100011 A
1%
#7000000
0%
#7010000
b100100 A
1%
#7020000
0%
#7030000
b100101 A
1%
#7040000
0%
#7050000
b100110 A
1%
#7060000
0%
#7070000
b100111 A
1%
#7080000
0%
#7090000
b101000 A
1%
#7100000
0%
#7110000
b101001 A
1%
#7120000
0%
#7130000
b101010 A
1%
#7140000
0%
#7150000
b101011 A
1%
#7160000
0%
#7170000
b101100 A
1%
#7180000
0%
#7190000
b101101 A
1%
#7200000
0%
#7210000
b101110 A
1%
#7220000
0%
#7230000
b101111 A
1%
#7240000
0%
#7250000
b110000 A
1%
#7260000
0%
#7270000
b110001 A
1%
#7280000
0%
#7290000
b110010 A
1%
#7300000
0%
#7310000
b110011 A
1%
#7320000
0%
#7330000
b110100 A
1%
#7340000
0%
#7350000
b110101 A
1%
#7360000
0%
#7370000
b110110 A
1%
#7380000
0%
#7390000
b110111 A
1%
#7400000
0%
#7410000
b111000 A
1%
#7420000
0%
#7430000
b111001 A
1%
#7440000
0%
#7450000
b111010 A
1%
#7460000
0%
#7470000
b111011 A
1%
#7480000
0%
#7490000
b111100 A
1%
#7500000
0%
#7510000
b111101 A
1%
#7520000
0%
#7530000
1H
b0 A
1%
#7540000
0%
#7550000
0!
1"
1E
0F
b11 C
b1 A
0H
b101 @
b10 G
1%
#7560000
0%
#7570000
b10 A
1%
#7580000
0%
#7590000
b11 A
1%
#7600000
0%
#7610000
b100 A
1%
#7620000
0%
#7630000
b101 A
1%
#7640000
0%
#7650000
b110 A
1%
#7660000
0%
#7670000
b111 A
1%
#7680000
0%
#7690000
b1000 A
1%
#7700000
0%
#7710000
b1001 A
1%
#7720000
0%
#7730000
b1010 A
1%
#7740000
0%
#7750000
b1011 A
1%
#7760000
0%
#7770000
b1100 A
1%
#7780000
0%
#7790000
b1101 A
1%
#7800000
0%
#7810000
b1110 A
1%
#7820000
0%
#7830000
b1111 A
1%
#7840000
0%
#7850000
b10000 A
1%
#7860000
0%
#7870000
b10001 A
1%
#7880000
0%
#7890000
b10010 A
1%
#7900000
0%
#7910000
b10011 A
1%
#7920000
0%
#7930000
b10100 A
1%
#7940000
0%
#7950000
b10101 A
1%
#7960000
0%
#7970000
b10110 A
1%
#7980000
0%
#7990000
b10111 A
1%
#8000000
0%
#8010000
b11000 A
1%
#8020000
0%
#8030000
b11001 A
1%
#8040000
0%
#8050000
b11010 A
1%
#8060000
0%
#8070000
b11011 A
1%
#8080000
0%
#8090000
b11100 A
1%
#8100000
0%
#8110000
b11101 A
1%
#8120000
0%
#8130000
b11110 A
1%
#8140000
0%
#8150000
b11111 A
1%
#8160000
0%
#8170000
b100000 A
1%
#8180000
0%
#8190000
b100001 A
1%
#8200000
0%
#8210000
b100010 A
1%
#8220000
0%
#8230000
b100011 A
1%
#8240000
0%
#8250000
b100100 A
1%
#8260000
0%
#8270000
b100101 A
1%
#8280000
0%
#8290000
b100110 A
1%
#8300000
0%
#8310000
b100111 A
1%
#8320000
0%
#8330000
b101000 A
1%
#8340000
0%
#8350000
b101001 A
1%
#8360000
0%
#8370000
b101010 A
1%
#8380000
0%
#8390000
b101011 A
1%
#8400000
0%
#8410000
b101100 A
1%
#8420000
0%
#8430000
b101101 A
1%
#8440000
0%
#8450000
b101110 A
1%
#8460000
0%
#8470000
b101111 A
1%
#8480000
0%
#8490000
b110000 A
1%
#8500000
0%
#8510000
b110001 A
1%
#8520000
0%
#8530000
b110010 A
1%
#8540000
0%
#8550000
b110011 A
1%
#8560000
0%
#8570000
b110100 A
1%
#8580000
0%
